{
  "replace": false,
  "values": [
    "minecraft:andesite_slab",
    "minecraft:cobbled_deepslate_slab",
    "minecraft:cobblestone_slab",
    "minecraft:deepslate_brick_slab",
    "minecraft:deepslate_tile_slab",
    "minecraft:diorite_slab",
    "minecraft:granite_slab",
    "minecraft:mossy_cobblestone_slab",
    "minecraft:polished_andesite_slab",
    "minecraft:polished_deepslate_slab",
    "minecraft:polished_diorite_slab",
    "minecraft:polished_granite_slab",
    {"id": "alexscaves:abyssmarine_brick_slab","required": false},
    {"id": "alexscaves:abyssmarine_slab","required": false},
    {"id": "alexscaves:coprolith_slab","required": false},
    {"id": "alexscaves:galena_brick_slab","required": false},
    {"id": "alexscaves:galena_slab","required": false},
    {"id": "alexscaves:guanostone_slab","required": false},
    {"id": "alexscaves:limestone_slab","required": false},
    {"id": "alexscaves:radrock_brick_slab","required": false},
    {"id": "alexscaves:radrock_slab","required": false},
    {"id": "born_in_chaos_v1:black_argillite_slab","required": false},
    {"id": "born_in_chaos_v1:black_argillitepressureplate","required": false},
    {"id": "quark:andesite_bricks_slab","required": false},
    {"id": "quark:andesite_bricks_vertical_slab","required": false},
    {"id": "quark:andesite_vertical_slab","required": false},
    {"id": "quark:calcite_bricks_slab","required": false},
    {"id": "quark:calcite_bricks_vertical_slab","required": false},
    {"id": "quark:calcite_slab","required": false},
    {"id": "quark:calcite_vertical_slab","required": false},
    {"id": "quark:cobbled_deepslate_vertical_slab","required": false},
    {"id": "quark:cobblestone_bricks_slab","required": false},
    {"id": "quark:cobblestone_bricks_vertical_slab","required": false},
    {"id": "quark:cobblestone_vertical_slab","required": false},
    {"id": "quark:deepslate_brick_vertical_slab","required": false},
    {"id": "quark:deepslate_tile_vertical_slab","required": false},
    {"id": "quark:diorite_bricks_slab","required": false},
    {"id": "quark:diorite_bricks_vertical_slab","required": false},
    {"id": "quark:diorite_vertical_slab","required": false},
    {"id": "quark:dripstone_block_slab","required": false},
    {"id": "quark:dripstone_block_vertical_slab","required": false},
    {"id": "quark:dripstone_bricks_slab","required": false},
    {"id": "quark:dripstone_bricks_vertical_slab","required": false},
    {"id": "quark:granite_bricks_slab","required": false},
    {"id": "quark:granite_bricks_vertical_slab","required": false},
    {"id": "quark:granite_vertical_slab","required": false},
    {"id": "quark:mossy_cobblestone_bricks_slab","required": false},
    {"id": "quark:mossy_cobblestone_bricks_vertical_slab","required": false},
    {"id": "quark:mossy_cobblestone_vertical_slab","required": false},
    {"id": "quark:polished_andesite_vertical_slab","required": false},
    {"id": "quark:polished_calcite_slab","required": false},
    {"id": "quark:polished_calcite_vertical_slab","required": false},
    {"id": "quark:polished_deepslate_vertical_slab","required": false},
    {"id": "quark:polished_diorite_vertical_slab","required": false},
    {"id": "quark:polished_dripstone_slab","required": false},
    {"id": "quark:polished_dripstone_vertical_slab","required": false},
    {"id": "quark:polished_granite_vertical_slab","required": false},
    {"id": "quark:polished_tuff_slab","required": false},
    {"id": "quark:polished_tuff_vertical_slab","required": false},
    {"id": "quark:tuff_bricks_slab","required": false},
    {"id": "quark:tuff_bricks_vertical_slab","required": false},
    {"id": "quark:tuff_slab","required": false},
    {"id": "quark:tuff_vertical_slab","required": false}
  ]
}